bardapi/__init__.py
bardapi/chat.py
bardapi/constants.py
bardapi/core.py
bardapi/core_async.py
bardapi/core_cookies.py
bardapi/utils.py
bardapi/models/__init__.py
bardapi/models/citation.py
bardapi/models/draft.py
bardapi/models/image.py
bardapi/models/result.py
bardapi/models/user_content.py
bardapi/models/tools/__init__.py
bardapi/models/tools/code.py
bardapi/models/tools/flight.py
bardapi/models/tools/gdocs.py
bardapi/models/tools/gworkspace.py
bardapi/models/tools/hotel.py
bardapi/models/tools/json.py
bardapi/models/tools/link.py
bardapi/models/tools/map.py
bardapi/models/tools/tool.py
bardapi/models/tools/tool_declaimer.py
bardapi/models/tools/youtube.py
bardapi-1.0.0.dist-info/LICENSE
bardapi-1.0.0.dist-info/METADATA
bardapi-1.0.0.dist-info/WHEEL
bardapi-1.0.0.dist-info/entry_points.txt
bardapi-1.0.0.dist-info/top_level.txt
bardapi-1.0.0.dist-info/RECORD
